{
	"ulid": "01JSH4W601DZPJTJM9Z1JKFTK0",
	"minTime": 1745371671850,
	"maxTime": 1745388000000,
	"stats": {
		"numSamples": 666335,
		"numSeries": 618,
		"numChunks": 5521
	},
	"compaction": {
		"level": 2,
		"sources": [
			"01JSGEDYBHJPBE83Q5373XH4AH",
			"01JSGG901HT52RJPVFMHH7Y8VN",
			"01JSGQ4QBHNG5SSYE8S9B3C0PY"
		],
		"parents": [
			{
				"ulid": "01JSGEDYBHJPBE83Q5373XH4AH",
				"minTime": 1745371671850,
				"maxTime": 1745373600000
			},
			{
				"ulid": "01JSGG901HT52RJPVFMHH7Y8VN",
				"minTime": 1745373606889,
				"maxTime": 1745380800000
			},
			{
				"ulid": "01JSGQ4QBHNG5SSYE8S9B3C0PY",
				"minTime": 1745380806969,
				"maxTime": 1745388000000
			}
		]
	},
	"version": 1
}